{
  "SerializedFilePath": "c:\\Users\\bemitchell\\repos\\cglabs\\cglabs-dashboard-demo\\code\\demoApp\\obj\\Debug\\net6.0\\project.razor.json",
  "FilePath": "c:\\Users\\bemitchell\\repos\\cglabs\\cglabs-dashboard-demo\\code\\demoApp\\todo.csproj",
  "Configuration": {
    "ConfigurationName": "MVC-3.0",
    "LanguageVersion": "6.0",
    "Extensions": [
      {
        "ExtensionName": "MVC-3.0"
      }
    ]
  },
  "ProjectWorkspaceState": {
    "TagHelpers": [],
    "CSharpLanguageVersion": 1000
  },
  "RootNamespace": "todo",
  "Documents": [
    {
      "FilePath": "c:\\Users\\bemitchell\\repos\\cglabs\\cglabs-dashboard-demo\\code\\demoApp\\Views\\Shared\\Error.cshtml",
      "TargetPath": "Views\\Shared\\Error.cshtml",
      "FileKind": "mvc"
    },
    {
      "FilePath": "c:\\Users\\bemitchell\\repos\\cglabs\\cglabs-dashboard-demo\\code\\demoApp\\Views\\Item\\Create.cshtml",
      "TargetPath": "Views\\Item\\Create.cshtml",
      "FileKind": "mvc"
    },
    {
      "FilePath": "c:\\Users\\bemitchell\\repos\\cglabs\\cglabs-dashboard-demo\\code\\demoApp\\Views\\Item\\Details.cshtml",
      "TargetPath": "Views\\Item\\Details.cshtml",
      "FileKind": "mvc"
    },
    {
      "FilePath": "c:\\Users\\bemitchell\\repos\\cglabs\\cglabs-dashboard-demo\\code\\demoApp\\Views\\Shared\\_ValidationScriptsPartial.cshtml",
      "TargetPath": "Views\\Shared\\_ValidationScriptsPartial.cshtml",
      "FileKind": "mvc"
    },
    {
      "FilePath": "c:\\Users\\bemitchell\\repos\\cglabs\\cglabs-dashboard-demo\\code\\demoApp\\Views\\Item\\Edit.cshtml",
      "TargetPath": "Views\\Item\\Edit.cshtml",
      "FileKind": "mvc"
    },
    {
      "FilePath": "c:\\Users\\bemitchell\\repos\\cglabs\\cglabs-dashboard-demo\\code\\demoApp\\Views\\Item\\Index.cshtml",
      "TargetPath": "Views\\Item\\Index.cshtml",
      "FileKind": "mvc"
    },
    {
      "FilePath": "c:\\Users\\bemitchell\\repos\\cglabs\\cglabs-dashboard-demo\\code\\demoApp\\Views\\Shared\\_Layout.cshtml",
      "TargetPath": "Views\\Shared\\_Layout.cshtml",
      "FileKind": "mvc"
    },
    {
      "FilePath": "c:\\Users\\bemitchell\\repos\\cglabs\\cglabs-dashboard-demo\\code\\demoApp\\Views\\_ViewImports.cshtml",
      "TargetPath": "Views\\_ViewImports.cshtml",
      "FileKind": "mvc"
    },
    {
      "FilePath": "c:\\Users\\bemitchell\\repos\\cglabs\\cglabs-dashboard-demo\\code\\demoApp\\Views\\Item\\Delete.cshtml",
      "TargetPath": "Views\\Item\\Delete.cshtml",
      "FileKind": "mvc"
    },
    {
      "FilePath": "c:\\Users\\bemitchell\\repos\\cglabs\\cglabs-dashboard-demo\\code\\demoApp\\Views\\_ViewStart.cshtml",
      "TargetPath": "Views\\_ViewStart.cshtml",
      "FileKind": "mvc"
    }
  ],
  "SerializationFormat": "0.3"
}